example_app/__init__.py
example_app/app.py
starlette_service_utils/__init__.py
starlette_service_utils/command.py
starlette_service_utils/common.py
tests/__init__.py
starlette_service_utils-0.1.2.dist-info/LICENSE.txt
starlette_service_utils-0.1.2.dist-info/METADATA
starlette_service_utils-0.1.2.dist-info/WHEEL
starlette_service_utils-0.1.2.dist-info/top_level.txt
starlette_service_utils-0.1.2.dist-info/RECORD
